{"keywords":"flush","results":[{"keywords":[{"keyword":"blush","isChanged":true}],"algorithmType":"SYN","algorithmMap":{"SYN":"Related"},"combinedKeyword":"blush"},{"keywords":[{"keyword":"rush","isChanged":true}],"algorithmType":"SYN","algorithmMap":{"SYN":"Related"},"combinedKeyword":"rush"},{"keywords":[{"keyword":"gush","isChanged":true}],"algorithmType":"SYN","algorithmMap":{"SYN":"Related"},"combinedKeyword":"gush"},{"keywords":[{"keyword":"bloom","isChanged":true}],"algorithmType":"SYN","algorithmMap":{"SYN":"Related"},"combinedKeyword":"bloom"},{"keywords":[{"keyword":"flower","isChanged":true}],"algorithmType":"SYN","algorithmMap":{"SYN":"Related"},"combinedKeyword":"flower"},{"keywords":[{"keyword":"sluice","isChanged":true}],"algorithmType":"SYN","algorithmMap":{"SYN":"Related"},"combinedKeyword":"sluice"},{"keywords":[{"keyword":"prime","isChanged":true}],"algorithmType":"SYN","algorithmMap":{"SYN":"Related"},"combinedKeyword":"prime"},{"keywords":[{"keyword":"scour","isChanged":true}],"algorithmType":"SYN","algorithmMap":{"SYN":"Related"},"combinedKeyword":"scour"},{"keywords":[{"keyword":"kick","isChanged":true}],"algorithmType":"SYN","algorithmMap":{"SYN":"Related"},"combinedKeyword":"kick"},{"keywords":[{"keyword":"boot","isChanged":true}],"algorithmType":"SYN","algorithmMap":{"SYN":"Related"},"combinedKeyword":"boot"},{"keywords":[{"keyword":"level","isChanged":true}],"algorithmType":"SYN","algorithmMap":{"SYN":"Related"},"combinedKeyword":"level"},{"keywords":[{"keyword":"affluent","isChanged":true}],"algorithmType":"SYN","algorithmMap":{"SYN":"Related"},"combinedKeyword":"affluent"},{"keywords":[{"keyword":"peak","isChanged":true}],"algorithmType":"SYN","algorithmMap":{"SYN":"Related"},"combinedKeyword":"peak"},{"keywords":[{"keyword":"even","isChanged":true}],"algorithmType":"SYN","algorithmMap":{"SYN":"Related"},"combinedKeyword":"even"},{"keywords":[{"keyword":"blossom","isChanged":true}],"algorithmType":"SYN","algorithmMap":{"SYN":"Related"},"combinedKeyword":"blossom"},{"keywords":[{"keyword":"bang","isChanged":true}],"algorithmType":"SYN","algorithmMap":{"SYN":"Related"},"combinedKeyword":"bang"},{"keywords":[{"keyword":"purge","isChanged":true}],"algorithmType":"SYN","algorithmMap":{"SYN":"Related"},"combinedKeyword":"purge"},{"keywords":[{"keyword":"heyday","isChanged":true}],"algorithmType":"SYN","algorithmMap":{"SYN":"Related"},"combinedKeyword":"heyday"},{"keywords":[{"keyword":"thrill","isChanged":true}],"algorithmType":"SYN","algorithmMap":{"SYN":"Related"},"combinedKeyword":"thrill"},{"keywords":[{"keyword":"loaded","isChanged":true}],"algorithmType":"SYN","algorithmMap":{"SYN":"Related"},"combinedKeyword":"loaded"}],"errors":null,"errorCode":null}